{
  "app": {
    "name": "Alain",
    "description": "Ng-zorro admin panel front-end framework"
  },
  "user": {
    "name": "Admin",
    "avatar": "./assets/tmp/img/avatar.jpg",
    "email": "cipchk@qq.com"
  },
  "menu": [
    {
      "text": "主导航",
      "group": true,
      "hideInBreadcrumb": true,
      "children": [
        {
          "text": "Dashboard",
          "icon": "anticon-dashboard",
          "children": [
            {
              "text": "分析页",
              "link": "/dashboard/analysis"
            },
            {
              "text": "工作台",
              "link": "/dashboard/workplace"
            }
          ]
        },
        {
          "text": "管理",
          "icon": "anticon-global",
          "children": [
            {
              "text": "Saas",
              "icon": "anticon-dashboard",
              "children": [
                {
                  "text": "用户",
                  "link": "/identity/users",
                  "shortcutRoot": true
                },
                {
                  "text": "角色",
                  "link": "/identity/roles"
                }
              ]
            },
            {
              "text": "管理",
              "icon": "anticon-global",
              "children": [
                {
                  "text": "Shop",
                  "link": "/identity/shop-list"
                },
                {
                  "text": "角色",
                  "link": "/identity/2"
                }
              ]
            },
            {
              "text": "Identity Server",
              "icon": "anticon-global",
              "children": [
                {
                  "text": "用户",
                  "link": "/identity/1"
                },
                {
                  "text": "角色",
                  "link": "/identity/1"
                }
              ]
            }
          ]
        },
        {
          "text": "商家管理",
          "icon": "anticon-dashboard",
          "children": [
            {
              "text": "商家列表",
              "link": "/shop-management"
            }
          ]
        },
        {
          "text": "访客管理",
          "icon": "anticon-dashboard",
          "children": [
            {
              "text": "表单列表",
              "link": "/visitor/forms"
            }
          ]
        },
        {
          "text": "开发专用",
          "icon": "anticon-dashboard",
          "children": [
            {
              "text": "登录信息",
              "link": "/demo/demo1"
            }
          ]
        }
      ]
    }
  ]
}